{"codeList":["from pymilvus import MilvusClient\n\nindex_params = MilvusClient.prepare_index_params()\n\nindex_params.add_index(\n    field_name=\"your_vector_field_name\", # Name of the vector field to be indexed\n    index_type=\"IVF_RABITQ\", # Will be introduced in Milvus 2.6\n    index_name=\"vector_index\", # Name of the index to create\n    metric_type=\"IP\", # IVF_RABITQ supports IP and COSINE\n    params={\n        \"nlist\": 1024, # IVF param, specifies the number of clusters\n    } # Index building params\n)\n"],"headingContent":"","anchorList":[{"label":"Entendendo a pesquisa vetorial e a compactação","href":"Understanding-Vector-Search-and-Compression","type":2,"isActive":false},{"label":"Uma breve introdução ao RaBitQ","href":"A-Brief-Intro-to-RaBitQ","type":2,"isActive":false},{"label":"Engenharia do RaBitQ em Milvus: da investigação académica à produção","href":"Engineering-RaBitQ-in-Milvus-From-Academic-Research-to-Production","type":2,"isActive":false},{"label":"O ganho de desempenho: 3× mais QPS com precisão comparável","href":"The-Performance-Gain-3×-More-QPS-with-Comparable-Accuracy","type":2,"isActive":false},{"label":"Conclusão","href":"Conclusion","type":2,"isActive":false},{"label":"Começar a usar o Milvus 2.6","href":"Getting-Started-with-Milvus-26","type":2,"isActive":false}]}