{"codeList":[],"headingContent":"How we used semantic search to make our search 10x smarter","anchorList":[{"label":"Schlüsselwortbasierte Suche","href":"Keyword-based-search","type":2,"isActive":false},{"label":"Vektorielle Darstellung","href":"Vector-representation","type":2,"isActive":false},{"label":"Auswahl einer Suchmaschine für die Einbettungsähnlichkeit","href":"Select-an-embedding-similarity-search-engine","type":2,"isActive":false},{"label":"Milvus-Cluster-Dienst","href":"Milvus-cluster-service","type":2,"isActive":false},{"label":"Wie beschleunigt die Vektorindizierung die Ähnlichkeitssuche?","href":"How-does-vector-indexing-accelerate-similarity-search","type":2,"isActive":false},{"label":"Sie fragen sich, wie es weitergeht?","href":"What-next-you-ask","type":2,"isActive":false},{"label":"Referenzen:","href":"References","type":2,"isActive":false}]}