{"codeList":[],"headingContent":"","anchorList":[{"label":"ما هي MMap؟","href":"What-is-MMap","type":2,"isActive":false},{"label":"من المستفيد من MMap؟","href":"Who-benefits-from-MMap","type":2,"isActive":false},{"label":"تمكين MMap في Milvus: تكوين بسيط","href":"Enabling-MMap-in-Milvus-a-simple-configuration","type":2,"isActive":false},{"label":"تحقيق التوازن: الأداء والتخزين وحدود النظام","href":"Striking-the-balance-performance-storage-and-system-limits","type":2,"isActive":false},{"label":"الطريق إلى الأمام: الابتكار المستمر والتحسينات التي تركز على المستخدم","href":"The-road-ahead-continuous-innovation-and-user-centric-enhancements","type":2,"isActive":false},{"label":"الخلاصة: إعادة تعريف التميز في معالجة البيانات مع Milvus MMap","href":"Conclusion-redefining-data-processing-excellence-with-Milvus-MMap","type":2,"isActive":false}]}