{"codeList":[],"headingContent":"","anchorList":[{"label":"مقدمة","href":"Introduction","type":2,"isActive":false},{"label":"فئات التكوين","href":"Configuration-Categories","type":2,"isActive":false},{"label":"تكوينات مكونات التبعية في ميلفوس","href":"Milvus-Dependency-Component-Configurations","type":2,"isActive":false},{"label":"تكوينات مكوّنات ميلفوس الداخلية","href":"Milvus-Internal-Component-Configurations","type":2,"isActive":false},{"label":"تكوينات وظيفية أخرى","href":"Other-Functional-Configurations","type":2,"isActive":false},{"label":"أمثلة على التكوين الواقعي","href":"Real-World-Configuration-Examples","type":2,"isActive":false},{"label":"الخلاصة","href":"Conclusion","type":2,"isActive":false}]}