{"codeList":[],"headingContent":"","anchorList":[{"label":"典型的なRAGパイプラインの仕組み","href":"How-a-Typical-RAG-Pipeline-Works","type":2,"isActive":false},{"label":"最大-最小のセマンティック・チャンキング：まず埋め込み、次にチャンク","href":"Max–Min-Semantic-Chunking-Embed-First-Chunk-Second","type":2,"isActive":false},{"label":"最大最小セマンティック・チャンキング戦略の仕組み","href":"How-the-Max–Min-Semantic-Chunking-Strategy-Works","type":2,"isActive":false},{"label":"最大最小意味チャンキングの長所と限界","href":"Strengths-and-Limitations-of-Max–Min-Semantic-Chunking","type":2,"isActive":false},{"label":"結論","href":"Conclusion","type":2,"isActive":false}]}