{"codeList":[],"headingContent":"","anchorList":[{"label":"私たちがMilvusを作り始めたのは、他にうまくいくものがなかったからです。","href":"We-Started-Building-Milvus-Because-Nothing-Else-Worked","type":2,"isActive":false},{"label":"Milvusのオープンソース化：公共での構築","href":"Open-Sourcing-Milvus-Building-in-Public","type":2,"isActive":false},{"label":"最も困難な決断やり直す","href":"The-Hardest-Decision-Starting-Over","type":2,"isActive":false},{"label":"AIですべてが加速するとき","href":"When-Everything-Accelerated-with-AI","type":2,"isActive":false},{"label":"Milvusを支えるチーム：Zilliz","href":"The-Team-Behind-Milvus-Zilliz","type":2,"isActive":false},{"label":"プロダクションにおける真のインパクトユーザーからの信頼","href":"Real-Impact-in-Production-The-Trust-from-Users","type":2,"isActive":false},{"label":"Zilliz Cloudを構築した理由エンタープライズ・グレードのベクター・データベース・アズ・ア・サービス","href":"Why-We-Built-Zilliz-Cloud-Enterprise-Grade-Vector-Database-as-a-Service","type":2,"isActive":false},{"label":"次なる課題ベクター・データレイク","href":"Whats-Next-Vector-Data-Lake","type":2,"isActive":false},{"label":"皆さんに感謝します！","href":"A-Big-Thanks-to-You-All","type":2,"isActive":false}]}