{"codeList":[],"headingContent":"How Does Milvus Schedule Query Tasks","anchorList":[{"label":"배경","href":"Background","type":2,"isActive":false},{"label":"기본 개념","href":"Basic-concepts","type":2,"isActive":false},{"label":"색인 구축","href":"Index-building","type":2,"isActive":false},{"label":"성능 최적화","href":"Performance-optimization","type":2,"isActive":false},{"label":"문제점 및 해결 방법","href":"Problems-and-solutions","type":2,"isActive":false},{"label":"향후 작업","href":"Future-work","type":2,"isActive":false}]}