{"codeList":[],"headingContent":"","anchorList":[{"label":"Понимание репликации, согласованности и консенсуса","href":"Understanding-replication-consistency-and-consensus","type":2,"isActive":false},{"label":"Репликация на основе консенсуса","href":"Consensus-based-replication","type":2,"isActive":false},{"label":"Стратегия репликации журналов для облачных и распределенных баз данных","href":"A-log-replication-strategy-for-cloud-native-and-distributed-database","type":2,"isActive":false},{"label":"Резюме","href":"Summary","type":2,"isActive":false},{"label":"Ссылки","href":"References","type":2,"isActive":false}]}