{"codeList":[],"headingContent":"","anchorList":[{"label":"什麼是 S3 相容儲存的 RDMA？","href":"What-is-RDMA-for-S3-compatible-storage","type":2,"isActive":false},{"label":"突破性的效能結果","href":"Breakthrough-Performance-Results","type":2,"isActive":false},{"label":"為什麼 AI 工作負載需要基於 S3 API 的物件儲存？","href":"Why-S3-API-based-Object-Storage-for-AI-Workloads","type":2,"isActive":false},{"label":"前進之路","href":"The-Road-Ahead","type":2,"isActive":false},{"label":"產業展望","href":"Industry-Perspectives","type":2,"isActive":false}]}